{
	"ImportPath": "github.com/intervention-engine/fhir",
	"GoVersion": "go1.6",
	"GodepVersion": "v74",
	"Packages": [
		"./..."
	],
	"Deps": [
		{
			"ImportPath": "github.com/bitly/go-simplejson",
			"Comment": "v0.5.0",
			"Rev": "aabad6e819789e569bd6aabf444c935aa9ba1e44"
		},
		{
			"ImportPath": "github.com/gin-gonic/gin",
			"Comment": "v1.0rc1-248-g4a6bc4a",
			"Rev": "4a6bc4aac4607e253bcda67c8c5bcda693d2388e"
		},
		{
			"ImportPath": "github.com/gin-gonic/gin/binding",
			"Comment": "v1.0rc1-248-g4a6bc4a",
			"Rev": "4a6bc4aac4607e253bcda67c8c5bcda693d2388e"
		},
		{
			"ImportPath": "github.com/gin-gonic/gin/render",
			"Comment": "v1.0rc1-248-g4a6bc4a",
			"Rev": "4a6bc4aac4607e253bcda67c8c5bcda693d2388e"
		},
		{
			"ImportPath": "github.com/golang/protobuf/proto",
			"Rev": "8d92cf5fc15a4382f8964b08e1f42a75c0591aa3"
		},
		{
			"ImportPath": "github.com/itsjamie/gin-cors",
			"Comment": "1.0.0",
			"Rev": "97b4a9da79331dfa2b6d35f4cdd1e50f5148859c"
		},
		{
			"ImportPath": "github.com/manucorporat/sse",
			"Rev": "ee05b128a739a0fb76c7ebd3ae4810c1de808d6d"
		},
		{
			"ImportPath": "github.com/pebbe/util",
			"Rev": "e0e04dfe647cbd76fc8a1fba55406e60a2e49a11"
		},
		{
			"ImportPath": "golang.org/x/net/context",
			"Rev": "5df5483e0518a11a6ef1e894c70236eb3f639557"
		},
		{
			"ImportPath": "gopkg.in/check.v1",
			"Rev": "4f90aeace3a26ad7021961c297b22c42160c7b25"
		},
		{
			"ImportPath": "gopkg.in/go-playground/validator.v8",
			"Comment": "v8.17.1",
			"Rev": "014792cf3e266caff1e916876be12282b33059e0"
		},
		{
			"ImportPath": "gopkg.in/mgo.v2",
			"Comment": "r2015.12.06-2-g03c9f3e",
			"Rev": "03c9f3ee4c14c8e51ee521a6a7d0425658dd6f64"
		},
		{
			"ImportPath": "gopkg.in/mgo.v2/bson",
			"Comment": "r2015.12.06-2-g03c9f3e",
			"Rev": "03c9f3ee4c14c8e51ee521a6a7d0425658dd6f64"
		},
		{
			"ImportPath": "gopkg.in/mgo.v2/dbtest",
			"Comment": "r2015.12.06-2-g03c9f3e",
			"Rev": "03c9f3ee4c14c8e51ee521a6a7d0425658dd6f64"
		},
		{
			"ImportPath": "gopkg.in/mgo.v2/internal/sasl",
			"Comment": "r2015.12.06-2-g03c9f3e",
			"Rev": "03c9f3ee4c14c8e51ee521a6a7d0425658dd6f64"
		},
		{
			"ImportPath": "gopkg.in/mgo.v2/internal/scram",
			"Comment": "r2015.12.06-2-g03c9f3e",
			"Rev": "03c9f3ee4c14c8e51ee521a6a7d0425658dd6f64"
		},
		{
			"ImportPath": "gopkg.in/tomb.v2",
			"Rev": "14b3d72120e8d10ea6e6b7f87f7175734b1faab8"
		}
	]
}
